LICENSE.txt
README.md
setup.cfg
setup.py
aether_client_sdk/__init__.py
aether_client_sdk.egg-info/PKG-INFO
aether_client_sdk.egg-info/SOURCES.txt
aether_client_sdk.egg-info/dependency_links.txt
aether_client_sdk.egg-info/requires.txt
aether_client_sdk.egg-info/top_level.txt
aether_client_sdk/workflow/__init__.py