Metadata-Version: 2.1
Name: aether-client-sdk
Version: 1.0.0
Summary: Aether Client SDK
Home-page: https://github.com/aether-labs/aether-sdk-python
Author: Calum Webb
Author-email: calumpeterwebb@icloud.com
License: UNKNOWN
Download-URL: https://github.com/aether-labs/aether-sdk-python/archive/refs/tags/1.0.0.tar.gz
Keywords: aether,aether-grpc,grpc,aether-labs,aether-sdk,sdk
Platform: UNKNOWN
Classifier: Development Status :: 3 - Alpha
Classifier: Intended Audience :: Developers
Classifier: Topic :: Software Development :: Build Tools
Classifier: License :: OSI Approved :: MIT License
Classifier: Programming Language :: Python :: 3.8
Provides-Extra: dev
